
[
    {
        "id": 20,
        "name":"Laptop",  
        "price":400,
        "brand":"HP",
        "size": 14,
        "describtion":"This is a laptop that is good for playing, working, studying and more feel free to purchase",
        "img":"laptop.png"  

    },
    {
        "id":21,
        "name":"Tablet Fire",  
        "price":200,
        "brand":"HP",
        "size": 14,
        "describtion":"This is a Tablet Fire that is good for playing, working, studying and more feel free to purchase" ,
        "img":"tablet.png"        
    },
    {
        "id":22,
        "name":"Mouse inalámbrico",  
        "price":300,
        "brand":"Lenovo",
        "size": 4,
        "describtion":"This is a Mouse inalámbrico  that is good for playing, working, studying and more feel free to purchase",
        "img":"mouse.png"          
    },
    {
        "id":23,
        "name":"Fire TV Stick 4K",  
        "price":400,
        "brand":"Fire TV Stick 4K",
        "size": 8,
        "describtion":"This is a Fire TV Stick that is good for wacthing movies, working, studying and more feel free to purchase" ,
        "img":"fireTvStick.jpg"         
    }

]